{"transcript":"dɪsˈɒnərd","exists":true,"definitions":["Brought shame or disgrace upon.","Failed to pay (a check or bill) when due.","Violated or disregarded (a promise or agreement)."],"examples":["His actions dishonored his family's name.","The bank dishonored the check due to insufficient funds.","They dishonored the treaty by invading the territory."],"lemma":"dishonor","lemmaPos":"verb","synonyms":["disgraced","shamed","debased","defiled"],"number":"singular","pastTenses":"dishonored","tense":"past","isIrregular":false,"source":"dishonored"}