{"transcript":"ˈɡrændˌfæm.li","exists":true,"definitions":["A household in which children are being raised by their grandparents or other extended family members without the parents present."],"examples":["The local community center offers support groups for every grandfamily.","She grew up in a grandfamily after her parents moved abroad."],"lemma":"grandfamily","lemmaPos":"noun","synonyms":["kinship care household","grandparent-headed household"],"number":"singular","pluralForm":"grandfamilies","source":"grandfamily"}