{"exists":true,"definitions":["To advance one's own position or career by ruthlessly exploiting or suppressing others","To treat someone with extreme disrespect or cruelty while pursuing personal gain"],"examples":["He reached the top by stepping on somebody's head at every promotion cycle.","You can't build a reputation by stepping on somebody's head."],"lemma":"step on somebody's head","lemmaPos":"verb phrase","synonyms":["climb over someone","step on toes","throw someone under the bus","walk all over someone"],"number":"singular","source":"stepping on somebody's head","transcript":""}