{"transcript":"miːn","exists":true,"definitions":["To intend to convey, indicate, or refer to (something); signify.","To have (something) as a purpose or intention.","To result in or involve (something); portend.","To be of a specified importance or significance."],"examples":["What does this word mean?","I didn't mean to hurt your feelings.","These clouds mean rain.","His friendship means a lot to me."],"lemma":"mean","lemmaPos":"verb","synonyms":["signify","intend","imply","denote"],"number":"singular","pastTenses":"meant, meant","tense":"present","isIrregular":true,"source":"mean"}