{"transcript":"ňąn…Ē…™z p…ôňąluňź É…ôn","exists":true,"definitions":["Harmful or annoying levels of noise, especially in an urban environment.","Unwanted or excessive sound that can have detrimental effects on human or animal health and well-being."],"examples":["Noise pollution is a major concern in big cities.","The factory was cited for excessive noise pollution.","Regulations aim to reduce noise pollution from airports."],"lemma":"noise pollution","lemmaPos":"noun","synonyms":["acoustic pollution","sound pollution"],"number":"singular","pluralForm":"noise pollutions","source":"noise pollution"}