{"transcript":"feɪz aʊt","exists":true,"definitions":["To gradually stop using or providing something.","To remove something in stages over a period of time."],"examples":["The company will phase out the old software next year.","They are phasing out incandescent light bulbs.","The government plans to phase out subsidies for fossil fuels."],"lemma":"phase out","lemmaPos":"verb","synonyms":["discontinue","eliminate","withdraw","remove"],"number":"singular","pastTenses":"phased out","tense":"present","isIrregular":false,"source":"phase out"}