{"transcript":"ˈlɛvɪteɪt","exists":true,"definitions":["To rise and float in the air, especially as if by magic or without visible support.","To cause to rise and float in the air."],"examples":["The magician appeared to levitate the assistant.","She claimed she could levitate objects with her mind.","The yogi was said to levitate during meditation."],"lemma":"levitate","lemmaPos":"verb","synonyms":["float","hover","rise"],"number":"singular","pastTenses":"levitated","tense":"present","isIrregular":false,"source":"levitate"}