{"transcript":"ˈɛnd.tə.ˈɛnd","exists":true,"definitions":["Relating to or denoting a process or system that covers the entire range from beginning to end.","Complete from start to finish; comprehensive."],"examples":["The company offers end-to-end solutions for data management.","We need an end-to-end encryption system.","They conducted an end-to-end test of the software."],"lemma":"end-to-end","lemmaPos":"adjective","synonyms":["comprehensive","complete","full-cycle","holistic"],"number":"singular","source":"end-to-end"}