{"transcript":"ˈmɛsɪŋ","exists":true,"definitions":["Engaging in playful or mischievous activity.","Interfering with something or someone.","Making something untidy or dirty.","Spending time idly or unproductively."],"examples":["They were messing around in the park.","Stop messing with my computer.","He's always messing up his room.","She spent the afternoon just messing about."],"lemma":"mess","lemmaPos":"verb","synonyms":["playing","tampering","cluttering","dawdling"],"number":"singular","pastTenses":"messed","tense":"present","isIrregular":false,"source":"messing"}