{"transcript":"틛t툮a톩틛ni틣z 틛m칝n.d톛r.톩n","exists":true,"definitions":["The most widely spoken form of the Chinese language, native to northern China.","A group of related Sinitic languages spoken across most of northern and southwestern China."],"examples":["She is fluent in Chinese - Mandarin.","Many people are learning Chinese - Mandarin.","The official language of China is Chinese - Mandarin."],"lemma":"Chinese - Mandarin","lemmaPos":"noun","synonyms":["Mandarin Chinese","Mandarin"],"number":"singular","pluralForm":"Chinese - Mandarin","source":"Chinese - Mandarin"}