{"transcript":"ˈdaɪəts","exists":true,"definitions":["Restricts oneself to small amounts or special kinds of food in order to lose weight or for medical reasons.","Eats sparingly or according to prescribed rules."],"examples":["She diets to stay in shape.","He diets for health reasons.","The doctor recommends she diets."],"lemma":"diet","lemmaPos":"verb","synonyms":["eats sparingly","restricts food","slims"],"number":"singular","pastTenses":"dieted","tense":"present","isIrregular":false,"source":"diets"}