{"transcript":"h…ôňąm…Ďňźd í…ôňĆna…™z","exists":true,"definitions":["to make uniform or similar in structure or composition","to treat milk so that the fat droplets are emulsified and the cream does not separate"],"examples":["The machine will homogenize the mixture.","They tried to homogenize the diverse culture."],"lemma":"homogenize","lemmaPos":"verb","synonyms":["standardize","unify","blend","equalize"],"number":"singular","pastTenses":"homogenized","tense":"present","isIrregular":false,"source":"homogenize"}