{"source":"ready meal","number":"singular","lemma":"ready meal","lemmaPos":"noun","definitions":["A pre-prepared meal, often sold in a supermarket, that requires minimal preparation (such as heating) before consumption.","A convenience food item designed for quick and easy consumption."],"examples":["She grabbed a ready meal for dinner.","The supermarket has a wide selection of ready meals.","Ready meals are popular among busy professionals."],"synonyms":["convenience meal","pre-packaged meal","microwave meal"],"transcript":"ˈrɛdi miːl","pluralForm":"ready meals"}