{"transcript":"kiːp ɒn ˈmuːvɪŋ","exists":true,"definitions":["To continue traveling or progressing without stopping","To persist in one's efforts despite difficulties","To maintain a state of activity or motion"],"examples":["Don't stop now, keep on moving.","We have to keep on moving to reach the camp by nightfall.","Even when it gets tough, you just have to keep on moving."],"lemma":"keep on moving","lemmaPos":"verb phrase","synonyms":["carry on","keep going","press on","forge ahead"],"number":"singular","source":"keep on moving"}