{"source":"shunt","number":"singular","lemma":"shunt","lemmaPos":"noun","definitions":["A device or path that allows electrical current to take an alternative route, usually to bypass a faulty point in a circuit.","A surgical procedure that creates a passage between two natural channels in the body, often to redirect blood flow or cerebrospinal fluid."],"examples":["The technician installed a shunt to bypass the faulty circuit.","Doctors decided to perform a shunt to relieve pressure."],"synonyms":["bypass","detour","reroute"],"transcript":"ʃʌnt"}