{"transcript":"stæmp aʊt","exists":true,"definitions":["To eliminate or suppress something completely, especially something undesirable.","To extinguish a fire by stepping on it repeatedly."],"examples":["The government aims to stamp out corruption.","They worked to stamp out the disease.","He stamped out the small campfire."],"lemma":"stamp out","lemmaPos":"verb","synonyms":["eradicate","eliminate","extinguish","suppress"],"number":"singular","pastTenses":"stamped out","tense":"present","isIrregular":false,"source":"stamp out"}