{"transcript":"ˈhæmər aʊt","exists":true,"definitions":["to reach an agreement or solution after a long or difficult discussion","to produce something through hard work or effort","to flatten or shape metal by striking it with a hammer"],"examples":["They managed to hammer out a deal.","The committee spent hours trying to hammer out the details.","The blacksmith had to hammer out the dents."],"lemma":"hammer out","lemmaPos":"verb","synonyms":["iron out","work out","thrash out","sort out"],"number":"singular","pastTenses":"hammered out","tense":"present","isIrregular":false,"source":"hammer out"}