{"transcript":"kənˈspaɪərd","exists":true,"definitions":["Made secret plans jointly to commit an unlawful or harmful act.","Seemed to work together to bring about a particular result, typically an unpleasant one."],"examples":["They conspired to overthrow the government.","The weather and the traffic conspired against us.","The group conspired to defraud the company."],"lemma":"conspire","lemmaPos":"verb","synonyms":["plotted","schemed","colluded","intrigued"],"number":"singular","pastTenses":"conspired","tense":"past","isIrregular":false,"source":"conspired"}