{"transcript":"ňąp…íli ňąm…Ďňźrk…™t","exists":true,"definitions":["A decentralized prediction market platform built on blockchain technology, allowing users to bet on the outcome of future events.","A specific instance or event within the PolyMarket platform where users can trade on predictions."],"examples":["I placed a bet on the election outcome on PolyMarket.","The PolyMarket for the new product launch was very active.","Many users are drawn to PolyMarket for its unique betting opportunities."],"lemma":"poly market","lemmaPos":"noun","synonyms":["prediction market","decentralized exchange","betting platform"],"number":"singular","pluralForm":"poly markets","source":"poly market"}