{"transcript":"ɑːr juː ˈhæŋɪŋ?","exists":true,"definitions":["To be suspended or supported from above.","To be in a state of uncertainty or indecision.","To be lingering or remaining in a place or situation."],"examples":["Are you hanging the picture on the wall?","Are you hanging around after work?","Are you hanging in there with your studies?"],"lemma":"hang","lemmaPos":"verb","synonyms":["dangle","suspend","linger","loiter"],"number":"singular","pastTenses":"hung, hung","tense":"present","isIrregular":true,"source":"are you hanging?"}