{"transcript":"tɜːrn ˈoʊvər ə nuː liːf","source":"turn over a new leaf","definitions":["To begin again, fresh; to make a new start.","To change one's behavior for the better; to improve one's character or conduct."],"examples":["After his release from prison, he promised to turn over a new leaf.","She decided to turn over a new leaf and start exercising regularly.","It's never too late to turn over a new leaf and pursue your dreams."],"lemma":"turn over a new leaf","lemmaPos":"verb","synonyms":["make a fresh start","start anew","reform","amend one's ways","mend one's ways"],"number":"singular"}