{"transcript":"ˈproʊfaɪl","exists":true,"definitions":["To represent or describe (someone or something) in a short, concise way.","To create a summary of a person or group, often for identification or analysis.","To subject (someone) to a profile or profiling, especially in the context of law enforcement or security."],"examples":["The journalist will profile the new CEO.","They profile customers to understand buying habits.","Security personnel often profile passengers."],"lemma":"profile","lemmaPos":"verb","synonyms":["characterize","describe","portray","sketch"],"number":"singular","pastTenses":"profiled","tense":"present","isIrregular":false,"source":"profile"}