{"transcript":"ˈtɛmpəˌrɛri tʃæt","exists":true,"definitions":["A digital conversation or messaging session designed to be deleted or expire after a short period.","A transient communication channel used for immediate, non-persistent interaction."],"examples":["Open a temporary chat for the quick meeting.","The app supports temporary chat for privacy.","All messages in the temporary chat were erased."],"lemma":"temporary chat","lemmaPos":"noun","synonyms":["ephemeral messaging","incognito chat","disappearing chat","transient conversation"],"number":"singular","pluralForm":"temporary chats","source":"temporary chat"}