{"transcript":"ˈtiːtərɪŋ","exists":true,"definitions":["Balancing unsteadily on one's feet.","Moving or swaying in a way that suggests a loss of balance.","Being on the verge of a significant change or outcome."],"examples":["She was teetering on the edge of the cliff.","The company is teetering on the brink of collapse.","He spent the afternoon teetering between decisions."],"lemma":"teeter","lemmaPos":"verb","synonyms":["wobbling","swaying","tottering","wavering"],"number":"singular","pastTenses":"teetered","tense":"present","isIrregular":false,"source":"teetering"}