{"transcript":"sɪmp","exists":true,"definitions":["To act like a simp; to show excessive adoration or subservience to someone, often in hopes of gaining their affection or attention.","To overvalue a person, often a woman, and cater to their every whim, typically without reciprocation."],"examples":["He would simp for her constantly, buying her gifts and doing favors.","Don't simp over someone who doesn't appreciate you.","Are you really going to simp for that streamer all day?"],"lemma":"simp","lemmaPos":"verb","synonyms":["fawn","adore","idolize","grovel"],"number":"singular","pastTenses":"simped","tense":"present","isIrregular":false,"source":"simp"}