{"transcript":"ˈprɑmptɪd","exists":true,"definitions":["Caused or brought about an action or feeling.","Assisted or encouraged someone to say or do something.","Inspired or motivated someone to act."],"examples":["His question prompted a lively discussion.","She was prompted by the director to speak louder.","The news prompted a surge in donations."],"lemma":"prompt","lemmaPos":"verb","synonyms":["incited","instigated","motivated","spurred","triggered"],"number":"singular","pastTenses":"prompted","tense":"past","isIrregular":false,"source":"prompted"}