{"transcript":"ˈnuːtər","exists":true,"definitions":["To remove the testicles of (a male animal) or the ovaries of (a female animal); to castrate or spay.","To make ineffective or powerless."],"examples":["We plan to neuter our cat next month.","The new regulations effectively neuter the committee's power.","They decided to neuter the stray dog."],"lemma":"neuter","lemmaPos":"verb","synonyms":["castrate","spay","emasculate","sterilize"],"number":"singular","pastTenses":"neutered","tense":"present","isIrregular":false,"source":"neuter"}