{"transcript":"kænt bɛr","exists":true,"definitions":["To be unable to tolerate or endure something or someone.","To strongly dislike something or someone."],"examples":["I can't bear the thought of losing you.","She can't bear to be alone.","They can't bear the noise."],"lemma":"can't bear","lemmaPos":"verb phrase","synonyms":["can't stand","detest","loathe","abhor"],"number":"singular","pastTenses":"couldn't bear, haven't been able to bear","tense":"present","isIrregular":true,"source":"can't bear"}