{"transcript":"ˈtʃɪŋmɪŋ","exists":true,"definitions":["A traditional Chinese festival on the 15th day after the spring equinox, when people visit the graves of their ancestors to clean them and make offerings.","The period of time around the Qingming festival."],"examples":["Many families travel long distances to observe Qingming.","Qingming is also known as Tomb-Sweeping Day.","During Qingming, special foods are often prepared."],"lemma":"Qingming","lemmaPos":"noun","synonyms":["Tomb-Sweeping Day","Ching Ming Festival"],"number":"singular","pluralForm":"Qingmings","source":"Qingming"}