{"exists":true,"definitions":["A process in which the nurse consciously uses her or his whole self to help the patient identify and then resolve problems.","A goal-directed form of communication used in healthcare to promote the physical and mental well-being of patients.","The application of communication skills to promote the physical and mental well-being of patients."],"examples":["Effective therapeutic communication is crucial for patient recovery.","Nurses are trained in therapeutic communication techniques.","Building trust through therapeutic communication."],"lemma":"therapeutic communication","lemmaPos":"noun","synonyms":["healing dialogue","supportive communication","patient-centered communication"],"number":"singular","pluralForm":"therapeutic communications","source":"therapeutic communication","transcript":""}