{"transcript":"prɪk","exists":true,"definitions":["To pierce slightly with a sharp point.","To cause a sharp, stinging pain.","To make a small hole in something.","To mark or outline by pricking.","To cause a sudden feeling of discomfort or unease."],"examples":["She pricked her finger on a needle.","A thorn pricked his skin.","The cold air pricked her cheeks.","He pricked the balloon with a pin.","A sense of guilt pricked his conscience."],"lemma":"prick","lemmaPos":"verb","synonyms":["pierce","puncture","sting","jab","stab"],"number":"singular","pastTenses":"pricked","tense":"present","isIrregular":false,"source":"prick"}