{"source":"postgraduate","number":"singular","lemma":"postgraduate","lemmaPos":"noun","definitions":["A student who has already obtained a first degree and is continuing their studies at a university for a more advanced qualification.","A course of study undertaken after completing a first degree."],"examples":["She is a postgraduate in astrophysics.","He enrolled in a postgraduate program.","The university offers various postgraduate degrees."],"synonyms":["grad student","researcher","master's student","doctoral student"],"transcript":"ˌpoʊstˈɡrædʒuət"}