{"transcript":"hɑːrt ˈpɛndənt","exists":true,"definitions":["A piece of jewelry, typically worn around the neck, featuring a charm or locket shaped like a heart.","A decorative item, often made of metal or stone, designed in the shape of a heart and suspended from a chain or cord."],"examples":["She received a beautiful Heart Pendant for her birthday.","The antique Heart Pendant was a family heirloom.","He chose a simple silver Heart Pendant for his girlfriend."],"lemma":"heart pendant","lemmaPos":"noun","synonyms":["heart necklace","heart charm","love pendant"],"number":"singular","pluralForm":"heart pendants","source":"Heart Pendant"}