{"transcript":"ˈfɑstərɪŋ","exists":true,"definitions":["Encouraging the development or growth of something, especially something desirable.","Bringing up a child that is not one's own by birth.","Promoting the growth or development of something."],"examples":["Fostering a sense of community is important.","The organization is fostering new talent.","They are fostering a child for the next year."],"lemma":"foster","lemmaPos":"verb","synonyms":["nurturing","promoting","cultivating","encouraging"],"number":"singular","pastTenses":"fostered","tense":"present","isIrregular":false,"source":"fostering"}