{"transcript":"staɪlz","exists":true,"definitions":["Designs or arranges hair in a particular way.","Designs or makes in a particular form.","Names or calls by a particular title or designation."],"examples":["She styles her hair every morning.","The architect styles buildings with a modern flair.","He styles himself as a connoisseur."],"lemma":"style","lemmaPos":"verb","synonyms":["designs","arranges","names","calls"],"number":"singular","pastTenses":"styled","tense":"present","isIrregular":false,"source":"styles"}