{"transcript":"蕦n藞pe瑟d 藞we瑟d蕭瑟z","exists":true,"definitions":["Wages that have been earned by an employee but have not yet been paid by the employer.","Compensation for work or services rendered that is due but has not been disbursed."],"examples":["The lawsuit was filed over unpaid wages.","Many workers are struggling due to unpaid wages.","The company faced penalties for unpaid wages."],"lemma":"unpaid wage","lemmaPos":"noun","synonyms":["outstanding wages","due wages","back pay"],"number":"plural","pluralForm":"unpaid wages","source":"unpaid wages"}