{"transcript":"liːv ɪn piːs","exists":true,"definitions":["To stop bothering or annoying someone.","To allow someone to be undisturbed or unmolested."],"examples":["Please leave me in peace for a while.","He just wants to be left in peace.","They decided to leave her in peace after the argument."],"lemma":"leave in peace","lemmaPos":"verb","synonyms":["let alone","stop bothering","desist"],"number":"singular","tense":"present","pastTenses":"left in peace, left in peace","isIrregular":true,"source":"leave in peace"}