{"transcript":"tə ɡrɪl ˈsʌmbədi","exists":true,"definitions":["To question someone intensely and at length, often in an aggressive or intimidating manner, to extract information or a confession.","To subject someone to severe and prolonged criticism or pressure."],"examples":["The detective grilled the suspect for hours.","My parents grilled me about where I had been all night.","The boss grilled him over the missed deadline."],"lemma":"to grill sb","lemmaPos":"verb","synonyms":["interrogate","question","cross-examine","pump","badger"],"number":"singular","pastTenses":"grilled sb","tense":"present","isIrregular":false,"source":"to grill sb"}