{"transcript":"braʊz","exists":true,"definitions":["To look through a book or magazine without reading it systematically.","To look at goods in a shop without any intention of buying them.","To feed on leaves, twigs, or other high-growing vegetation."],"examples":["She likes to browse in bookstores.","We spent the afternoon browsing the shops.","Deer browse on the tender shoots."],"lemma":"browse","lemmaPos":"verb","synonyms":["scan","skim","graze","peruse"],"number":"singular","pastTenses":"browsed","tense":"present","isIrregular":false,"source":"brows"}