{"transcript":"sʌks","exists":true,"definitions":["To draw liquid or air into the mouth by the action of the lips and tongue.","To be very bad, unpleasant, or inadequate.","To draw something in a specified direction by suction.","To absorb or take in something.","To perform fellatio on someone."],"examples":["The baby sucks its thumb.","This movie sucks.","The vacuum cleaner sucks up dirt.","The plant sucks moisture from the soil.","He sucks his partner."],"lemma":"suck","lemmaPos":"verb","synonyms":["draw","absorb","be awful","be terrible"],"number":"singular","pastTenses":"sucked","tense":"present","isIrregular":false,"source":"sucks"}