{"source":"carriers","number":"plural","lemma":"carrier","lemmaPos":"noun","definitions":["Entities or objects that transport or convey items or people from one place to another.","Individuals or organisms that harbor a disease-causing organism but are asymptomatic themselves.","Companies or organizations that provide telecommunications or transport services."],"examples":["The disease spread quickly due to human carriers.","Mobile carriers offer various plans.","The carriers arrived on time."],"synonyms":["transporter","conveyor","bearer","transmitter"],"transcript":"ˈkær.i.ərz"}