{"transcript":"ˈfeɪvərɪŋ","exists":true,"definitions":["Showing approval or preference for.","Treating with partiality.","Being advantageous to.","Resembling one of the parents or relatives."],"examples":["The new policy is favoring small businesses.","She is favoring her left leg after the injury.","The artist is favoring bright colors in her latest work.","He is favoring his mother's side of the family."],"lemma":"favor","lemmaPos":"verb","synonyms":["preferring","supporting","liking","advantaging"],"number":"singular","pastTenses":"favored","tense":"present","isIrregular":false,"source":"favoring"}