{"exists":true,"definitions":["A setting or configuration within VirtualBox that grants the virtual machine access to USB devices connected to the host computer.","The authorization required for a VirtualBox guest operating system to interact with and utilize USB hardware."],"examples":["Configuring VirtualBox/USB permission is crucial for device passthrough.","Without proper VirtualBox/USB permission, the scanner won't work in the VM."],"lemma":"VirtualBox/USB permission","lemmaPos":"noun","synonyms":["USB passthrough setting","USB access right","USB device authorization"],"number":"singular","pluralForm":"VirtualBox/USB permissions","source":"VirtualBox/USB permission","transcript":""}