{"transcript":"/ˈrʌnəweɪ ˌæplɪˈkeɪʃənz/","source":"runaway applications","definitions":["Software programs or processes that consume an excessive amount of system resources (CPU, memory, disk I/O, etc.) without proper control or termination, often leading to system instability or unresponsiveness."],"examples":["The server crashed due to runaway applications.","Identifying runaway applications is crucial for system maintenance.","A memory leak can cause runaway applications."],"lemma":"runaway application","lemmaPos":"noun","synonyms":["resource-hogging applications","uncontrolled applications","errant applications"],"number":"plural"}