{"transcript":"rɪˈvɜːrbəreɪtɪŋ","exists":true,"definitions":["Producing an echo or series of echoes.","Having a continuing and far-reaching effect.","Being repeated several times as an echo."],"examples":["The sound was reverberating through the canyon.","His words were reverberating in her mind.","The impact of the decision is still reverberating."],"lemma":"reverberate","lemmaPos":"verb","synonyms":["echoing","resounding","vibrating"],"number":"singular","pastTenses":"reverberated","tense":"present","isIrregular":false,"source":"reverberating"}