{"transcript":"flɪŋ","exists":true,"definitions":["throw or hurl forcefully","move or push oneself or something suddenly and impetuously","have a brief, casual romantic or sexual relationship"],"examples":["She will fling the ball across the field.","He tends to fling himself into new projects.","They had a brief fling last summer."],"lemma":"fling","lemmaPos":"verb","synonyms":["throw","hurl","toss","cast"],"number":"singular","pastTenses":"flung, flung","tense":"present","isIrregular":true,"source":"fling"}