{"transcript":"spɪn","exists":true,"definitions":["To turn or cause to turn rapidly.","To draw out and twist fibers into thread or yarn.","To present information in a particular way, especially to make it seem more favorable.","To revolve quickly on an axis or pivot."],"examples":["The dancer began to spin.","She can spin wool into yarn.","The politician tried to spin the story.","The top will spin for a long time."],"lemma":"spin","lemmaPos":"verb","synonyms":["rotate","revolve","whirl","twirl"],"number":"singular","pastTenses":"spun, spun","tense":"present","isIrregular":true,"source":"spin"}