{"transcript":"ňąsa…™f…ôn…™Ňč","exists":true,"definitions":["The act or process of drawing off liquid through a siphon.","The act of illicitly or unfairly drawing off or transferring funds or resources."],"examples":["The siphoning of fuel from the tank was a slow process.","Authorities investigated the siphoning of public funds.","The siphoning of water from the pool helped lower the level."],"lemma":"siphon","lemmaPos":"verb","synonyms":["extraction","drainage","diversion","misappropriation"],"number":"singular","pluralForm":"siphonings","source":"siphoning"}