{"transcript":"tʌks","exists":true,"definitions":["Pushes, folds, or turns something into a small space or a concealed position.","Pulls up a part of a garment or other item of cloth so as to shorten it or hold it in a particular position.","Eats food with gusto or in large quantities."],"examples":["He tucks his shirt into his pants.","The bird tucks its head under its wing.","She tucks into her dinner with enthusiasm."],"lemma":"tuck","lemmaPos":"verb","synonyms":["folds","inserts","stuffs","eats"],"number":"singular","pastTenses":"tucked","tense":"present","isIrregular":false,"source":"tucks"}