{"number":"singular","lemma":"settle","lemmaPos":"verb","definitions":["to resolve or reach an agreement about a dispute","to establish a residence","to become calm or composed","to pay a debt or bill","to sink gradually"],"examples":["They settled the argument.","She plans to settle in the countryside.","He settled down after the commotion.","They settled the invoice yesterday.","The dust settled on the surface."],"synonyms":["resolve","reconcile","establish","inhabit","calm"],"transcript":"ˈsɛtəl","source":"settle"}