{"transcript":"ˌoʊvərˈsiː","exists":true,"definitions":["To supervise a person or their work, or to be in charge of a project or activity.","To watch over and direct a group of people or a task."],"examples":["She will oversee the entire project.","A manager was hired to oversee the new department.","The committee oversees the budget."],"lemma":"oversee","lemmaPos":"verb","synonyms":["supervise","manage","direct","monitor","inspect"],"number":"singular","pastTenses":"oversaw, overseen","tense":"present","isIrregular":true,"source":"oversee"}