{"transcript":"m…ôňąt É ä…ôr ňą…™ntuňź","exists":true,"definitions":["To develop or grow into a more advanced, complete, or adult form or state.","To reach a stage of full development or readiness for a particular role or function."],"examples":["The caterpillar will mature into a butterfly.","He hopes the startup will mature into a major company.","The young artist's style began to mature into something unique."],"lemma":"mature into","lemmaPos":"verb","synonyms":["develop into","grow into","evolve into","blossom into"],"number":"singular","pastTenses":"matured into","tense":"present","isIrregular":false,"source":"mature into"}