{"transcript":"tʃɛks","exists":true,"definitions":["Examines something in order to verify its accuracy or quality.","Stops or slows the progress of something.","Makes a mark (✓) to indicate that something has been noted or completed.","Deposits a financial check."],"examples":["The manager checks the reports daily.","He checks his email every hour.","The doctor checks the patient's vital signs.","She checks her coat at the door."],"lemma":"check","lemmaPos":"verb","synonyms":["examines","verifies","inspects","monitors"],"number":"singular","pastTenses":"checked","tense":"present","isIrregular":false,"source":"checks"}