{"source":"christmases","number":"plural","lemma":"Christmas","lemmaPos":"proper noun","definitions":["The festivals celebrating the birth of Jesus Christ observed on December 25 in Western Christianity.","The period around December 25 typically associated with the exchange of gifts, family gatherings, and various traditions."],"examples":["We had wonderful christmases together.","There were several memorable christmases over the years."],"synonyms":["Yule","Noel","Xmas"],"transcript":"ˈkrɪs.məs.ɪz"}