{"transcript":"ˈfɪlɪp","exists":true,"definitions":["A male given name, from Greek meaning 'lover of horses'.","Several kings of Macedon, including Philip II, father of Alexander the Great.","One of the twelve apostles of Jesus Christ.","A number of European monarchs, particularly in Spain and France.","A common surname."],"examples":["Philip is a common name.","King Philip II was a powerful ruler.","Saint Philip was an apostle.","Philip Glass is a famous composer."],"lemma":"Philip","lemmaPos":"proper noun","synonyms":["Phil","Pip"],"number":"singular","pluralForm":"Philips","source":"Philip"}