{"transcript":"trɪp","exists":true,"definitions":["Catch one's foot on something and stumble or fall.","Go on a journey or excursion.","Activate a mechanism, especially a switch or alarm.","Experience a hallucinogenic drug trip."],"examples":["She might trip on the rug.","They plan to trip to the mountains.","The alarm will trip if opened.","He started to trip after taking the pill."],"lemma":"trip","lemmaPos":"verb","synonyms":["stumble","journey","activate","hallucinate"],"number":"singular","pastTenses":"tripped","tense":"present","isIrregular":false,"source":"trip"}