{"transcript":"ˈriːleɪ","exists":true,"definitions":["To receive and pass on (information or a message).","To pass (a message or information) from one person or place to another.","To broadcast (television or radio signals).","To replace (something) with a new or different one."],"examples":["Please relay the message to the team.","The station will relay the live broadcast.","They had to relay the old pipes.","He relayed the instructions to his subordinates."],"lemma":"relay","lemmaPos":"verb","synonyms":["transmit","convey","communicate","broadcast","pass on"],"number":"singular","pastTenses":"relayed","tense":"present","isIrregular":false,"source":"relay"}