{"transcript":"doʊz ɒf","exists":true,"definitions":["To fall asleep unintentionally, especially for a short period.","To begin to sleep, often without meaning to."],"examples":["He started to doze off during the long lecture.","I often doze off on the couch after dinner.","She was so tired she began to doze off at her desk."],"lemma":"doze off","lemmaPos":"verb","synonyms":["nod off","drift off","drop off","fall asleep"],"number":"singular","pastTenses":"dozed off","tense":"present","isIrregular":false,"source":"doze off"}