{"transcript":"m…ôňąl…õst…™Ňč","exists":true,"definitions":["Harassing or attacking (someone), especially a child, sexually.","Annoying, interfering with, or troubling someone in an aggressive or persistent manner."],"examples":["He was accused of molesting several young people.","The constant noise was molesting their peace.","She reported him for molesting her at work."],"lemma":"molest","lemmaPos":"verb","synonyms":["harassing","abusing","assaulting","annoying","bothering"],"number":"singular","pastTenses":"molested","tense":"present","isIrregular":false,"source":"molesting"}