{"transcript":"kriˈeɪtɪŋ","exists":true,"definitions":["The act of bringing something into existence.","The process of designing or imagining something.","The act of causing something to happen or exist."],"examples":["She is creating a new sculpture.","They are creating a lot of noise.","He is creating a plan for the project."],"lemma":"create","lemmaPos":"verb","synonyms":["making","producing","designing","forming"],"number":"singular","pastTenses":"created","tense":"present","isIrregular":false,"source":"creating"}