{"transcript":"ˌriːnɪˈɡoʊʃieɪt","exists":true,"definitions":["To negotiate again in order to change the terms of a previous agreement.","To discuss and agree on new terms for something, such as a contract or debt."],"examples":["They decided to renegotiate the contract.","The company wants to renegotiate the loan terms.","We need to renegotiate the price with the supplier."],"lemma":"renegotiate","lemmaPos":"verb","synonyms":["rediscuss","rework","rehash"],"number":"singular","pastTenses":"renegotiated","tense":"present","isIrregular":false,"source":"renegotiate"}