{"transcript":"sɛns ʌv əˈtʃivmənt","exists":true,"definitions":["A feeling of pride and satisfaction that comes from completing something difficult or important."],"examples":["Finishing the marathon gave her a great sense of achievement.","He felt a deep sense of achievement after earning his degree."],"lemma":"sense of achievement","lemmaPos":"noun","synonyms":["sense of accomplishment","fulfillment","satisfaction","pride"],"number":"singular","pluralForm":"senses of achievement","source":"sense of achievement"}