{"source":"NotebookLM","number":"singular","lemma":"NotebookLM","lemmaPos":"proper noun","definitions":["A research and writing assistant developed by Google that uses generative AI to help users synthesize information, brainstorm ideas, and create content.","A Google product designed to work with a user's own documents, allowing them to upload sources and then ask questions, summarize, and generate ideas based on those specific materials."],"examples":["I used NotebookLM to help me organize my research papers.","NotebookLM can summarize long documents quickly.","Brainstorming ideas with NotebookLM made the writing process smoother."],"synonyms":["AI research assistant","Google AI tool","generative AI for research"],"transcript":"ˈnoʊtbʊk ɛl ɛm"}