{"transcript":"ˈʃaʊər","exists":true,"definitions":["To wash oneself in a shower.","To give someone a shower.","To give someone a lot of gifts or attention.","To fall in a shower, as of rain or small objects."],"examples":["I need to shower before dinner.","She showered her with compliments.","The confetti showered down on the crowd."],"lemma":"shower","lemmaPos":"verb","synonyms":["bathe","douse","lavish","rain"],"number":"singular","pastTenses":"showered","tense":"present","isIrregular":false,"source":"shower"}