{"transcript":"ˈnɪkˌneɪm","exists":true,"definitions":["To give a descriptive or familiar name to a person or thing instead of or in addition to the real name.","To refer to someone or something by a nickname."],"examples":["They nickname him 'Speedy' because he runs so fast.","She was nicknamed 'Princess' by her grandparents.","The band was nicknamed 'The Fab Four'."],"lemma":"nickname","lemmaPos":"verb","synonyms":["call","dub","label","designate"],"number":"singular","pastTenses":"nicknamed","tense":"present","isIrregular":false,"source":"nickname"}