{"transcript":"bæŋk əˈkaʊnts","exists":true,"definitions":["Arrangements with a financial institution to store, deposit, and withdraw money.","Records of financial transactions between a customer and a bank."],"examples":["She manages multiple bank accounts.","Interest rates on bank accounts vary.","Check your bank accounts for fraud."],"lemma":"bank account","lemmaPos":"noun","synonyms":["accounts","checking accounts","savings accounts","deposits"],"number":"plural","pluralForm":"bank accounts","source":"bank accounts"}