{"transcript":"藢p蓹rsp蓹藞k忙s蓹ti","exists":true,"definitions":["The quality of having a ready insight into things.","A keenness of mental perception and understanding."],"examples":["Her perspicacity in business deals was legendary.","He admired her perspicacity in analyzing complex problems.","The detective's perspicacity led to the quick resolution of the case."],"lemma":"perspicacity","lemmaPos":"noun","synonyms":["acuity","discernment","insight","shrewdness","sagacity"],"number":"singular","pluralForm":"perspicacities","source":"perspicacity"}