{"transcript":"ˈstɪmjəˌleɪts","exists":true,"definitions":["Encourages interest or activity in something.","Causes a physiological or psychological response in an organ or tissue.","Increases the activity or rate of something."],"examples":["The aroma of coffee stimulates the senses.","Exercise stimulates blood circulation.","The new policy stimulates economic growth."],"lemma":"stimulate","lemmaPos":"verb","synonyms":["arouses","incites","promotes","activates"],"number":"singular","pastTenses":"stimulated","tense":"present","isIrregular":false,"source":"stimulates"}