{"number":"singular","lemma":"senate","lemmaPos":"noun","definitions":["A legislative or governing body, particularly the upper house of the legislature in various countries, including the United States.","A governing or advisory council within certain organizations or institutions, especially in universities."],"examples":["The Senate passed the bill.","He was elected to the Senate.","The university senate sets academic policies."],"synonyms":["congress","assembly","council","legislature"],"transcript":"ˈsɛnɪt","source":"senate"}