{"source":"installations","number":"plural","lemma":"installation","lemmaPos":"noun","definitions":["the action or process of installing something","a large piece of equipment installed for use","a military camp or base","a work of art that frequently involves the construction of a total environments"],"examples":["The installations were completed last week.","Art installations engage viewers.","The military installations are secure."],"synonyms":["setup","infrastructure","facility","base"],"transcript":"ˌɪnstəˈleɪʃənz"}