{"transcript":"ˈstraɪkɪŋ","exists":true,"definitions":["The action of hitting or an act of delivering a blow.","A sudden and forceful impact.","The act of workers refusing to work as a form of protest, a strike."],"examples":["The striking of the clock announced midnight.","The striking of the match produced a flame.","The union called for a striking to demand better wages."],"lemma":"strike","lemmaPos":"verb","synonyms":["hit","blow","impact","strike"],"number":"singular","pluralForm":"strikings","source":"striking"}