{"transcript":"riːtʃ aʊt","exists":true,"definitions":["To make an effort to communicate with someone, often to offer help or support.","To extend one's hand or arm to touch or grasp something or someone."],"examples":["She decided to reach out to her old friend after many years.","The company will reach out to customers for feedback.","He reached out his hand to steady her."],"lemma":"reach out","lemmaPos":"verb","synonyms":["contact","connect","extend"],"number":"singular","pastTenses":"reached out","tense":"present","isIrregular":false,"source":"reach out"}