{"transcript":"ˈhɪstəri bʌfs","exists":true,"definitions":["People who are very enthusiastic and knowledgeable about history.","Individuals with a strong interest in historical events, figures, and periods."],"examples":["History buffs often visit museums.","The tour was designed for history buffs.","Many history buffs enjoy reading biographies."],"lemma":"history buff","lemmaPos":"noun","synonyms":["history enthusiasts","history lovers","history aficionados"],"number":"plural","pluralForm":"history buffs","source":"history buffs"}