{"transcript":"ˈkiː tæɡ","exists":true,"definitions":["A small tag or label attached to a key or a set of keys, often used for identification or to hold information.","A small, often plastic, item designed to be attached to a key ring, sometimes used for promotional purposes or as a souvenir."],"examples":["I wrote my phone number on the key tag.","The hotel gave us a key tag with their logo.","He fumbled for the correct key tag in his pocket."],"lemma":"key tag","lemmaPos":"noun","synonyms":["keychain","key fob","key ring tag"],"number":"singular","pluralForm":"key tags","source":"key tag"}