{"transcript":"ˈrɪdɪkjuːl ˈsʌmwʌn","exists":true,"definitions":["To make fun of someone or something in a mocking or contemptuous way.","To subject someone to laughter, derision, or scorn."],"examples":["It's not kind to ridicule someone for their mistakes.","He would often ridicule someone who expressed an unpopular opinion.","They tried to ridicule someone who was different, but she stood her ground."],"lemma":"ridicule someone","lemmaPos":"verb","synonyms":["mock","deride","scoff at","taunt","make fun of"],"number":"singular","tense":"present","pastTenses":"ridiculed someone","isIrregular":false,"source":"ridicule someone"}