{"transcript":"ˈeɪliəneɪts","exists":true,"definitions":["Causes (someone) to feel isolated or estranged.","Transfers ownership of (property or rights) to another person or group."],"examples":["His constant criticism alienates his friends.","The company alienates its assets to a subsidiary.","Her behavior alienates potential allies."],"lemma":"alienate","lemmaPos":"verb","synonyms":["estrange","antagonize","transfer","cede"],"number":"singular","tense":"present","pastTenses":"alienated","isIrregular":false,"source":"alienates"}