{"transcript":"ˈɑkjəˌpaɪɪŋ","exists":true,"definitions":["Engaging the attention or time of someone.","Residing in or having possession of a place.","Filling or taking up space or time."],"examples":["The new project is occupying all her time.","They are currently occupying the building.","The large sofa is occupying most of the living room."],"lemma":"occupy","lemmaPos":"verb","synonyms":["inhabiting","possessing","filling","engaging"],"number":"singular","pastTenses":"occupied","tense":"present","isIrregular":false,"source":"occupying"}