{"transcript":"ˈwaɪərləs ˈraʊtər","exists":true,"definitions":["A device that performs the functions of a router and also includes the functions of a wireless access point.","A networking device that forwards data packets between computer networks and provides wireless connectivity to devices."],"examples":["Reset the wireless router.","The wireless router is blinking.","Connect to the wireless router."],"lemma":"wireless router","lemmaPos":"noun","synonyms":["Wi-Fi router","WLAN router","access point"],"number":"singular","pluralForm":"wireless routers","source":"wireless router"}