{"transcript":"ˈdʒɛriˌmændər","exists":true,"definitions":["To manipulate the boundaries of an electoral constituency so as to favor one party or class.","To divide a geographic area into voting districts in a way that gives one political party an unfair advantage."],"examples":["The party tried to gerrymander the districts.","They gerrymander to ensure a win."],"lemma":"gerrymander","lemmaPos":"verb","synonyms":["manipulate","rig","falsify","engineer"],"number":"singular","pastTenses":"gerrymandered","tense":"present","isIrregular":false,"source":"gerrymander"}