{"transcript":"ˌoʊvərˈsiːz","exists":true,"definitions":["Supervises a person or their work, especially in an official capacity.","Manages or directs an activity or a project."],"examples":["The manager oversees the entire department.","She oversees the development of new software.","He oversees the budget for the project."],"lemma":"oversee","lemmaPos":"verb","synonyms":["supervises","manages","directs","monitors"],"number":"singular","pastTenses":"oversaw, overseen","tense":"present","isIrregular":true,"source":"oversees"}