{"transcript":"ˌriːˈraɪt","exists":true,"definitions":["Write again so as to alter or improve.","Write a new version of a piece of writing.","Change the form or structure of something, especially a computer program or piece of code."],"examples":["She decided to rewrite her essay for a better grade.","The director asked the screenwriter to rewrite the ending of the movie.","We need to rewrite the entire module to fix the bug."],"lemma":"rewrite","lemmaPos":"verb","synonyms":["revise","redraft","rework","amend"],"number":"singular","pastTenses":"rewrote, rewritten","tense":"present","isIrregular":true,"source":"rewrite"}