{"transcript":"krip ɪn","exists":true,"definitions":["To gradually and almost imperceptibly begin to be present or to affect something.","To enter or appear slowly and unnoticed."],"examples":["Errors began to creep in as the project progressed.","A sense of unease started to creep in.","New regulations will creep in over the next few months."],"lemma":"creep in","lemmaPos":"phrasal verb","synonyms":["slip in","sneak in","edge in","seep in"],"number":"singular","pastTenses":"crept in, crept in","tense":"present","isIrregular":true,"source":"creep in"}