{"transcript":"ňąre…™t É…ôl t√¶n st…úrn","exists":true,"definitions":["Rache Tan-Stern is a fictional character from the web series 'The Guild'.","Rache Tan-Stern is known for her role as the character 'Bladezz' in 'The Guild'."],"examples":["Rache Tan-Stern portrayed Bladezz.","Fans often discuss Rache Tan-Stern's performance.","The character played by Rache Tan-Stern was popular."],"lemma":"Rache Tan-Stern","lemmaPos":"proper noun","synonyms":["Bladezz (character name)"],"number":"singular","pluralForm":"Rache Tan-Sterns","source":"Rache Tan-Stern"}