{"transcript":"ˈpoʊstɪd","exists":true,"definitions":["To display a notice or sign in a public place.","To send a letter or parcel by mail.","To publish something on the internet.","To assign someone to a particular place or duty.","To make an entry in an account book."],"examples":["The notice was posted on the bulletin board.","She posted the letter yesterday.","He posted an update on his blog.","The soldier was posted to a new base.","The accountant posted the transaction."],"lemma":"post","lemmaPos":"verb","synonyms":["mailed","published","assigned","displayed"],"number":"singular","pastTenses":"posted","tense":"past","isIrregular":false,"source":"posted"}