{"transcript":"slʌm","exists":true,"definitions":["To visit slums, especially out of curiosity or for charitable purposes.","To spend time in a squalid or degraded environment, often for a short period and for a specific purpose, sometimes implying a temporary lowering of one's standards."],"examples":["They decided to slum it in a cheap motel for the night.","He used to slum around with artists and musicians.","She would often slum in the poorer districts to understand their struggles."],"lemma":"slum","lemmaPos":"verb","synonyms":["rough it","degrade","lower oneself"],"number":"singular","pastTenses":"slummed","tense":"present","isIrregular":false,"source":"slum"}