{"transcript":"ˈbɜrbəl","exists":true,"definitions":["To make a continuous murmuring sound, like that of a shallow stream or boiling water.","To speak in a rapid, inarticulate, and often excited manner."],"examples":["The brook burbled over the rocks.","She burbled on about her new puppy.","The coffee machine burbled as it brewed."],"lemma":"burble","lemmaPos":"verb","synonyms":["gurgle","murmur","babble","chatter"],"number":"singular","pastTenses":"burbled","tense":"present","isIrregular":false,"source":"burble"}