{"transcript":"ˈlaɪt moʊd","exists":true,"definitions":["A display setting on electronic devices that uses a light-colored background with dark text and elements.","The visual theme of a user interface characterized by a predominantly white or light background."],"examples":["Many users prefer light mode for daytime use.","Switching to light mode can sometimes improve readability.","The app offers both dark and light mode options."],"lemma":"light mode","lemmaPos":"noun","synonyms":["day mode","white mode"],"number":"singular","pluralForm":"light modes","source":"light mode"}