{"transcript":"smɪrd","exists":true,"definitions":["Covered or marked with a greasy or sticky substance.","Damaged the good reputation of someone or something.","Spread a substance messily or thinly over a surface."],"examples":["His face was smeared with chocolate.","The politician was smeared by false accusations.","She smeared butter on the toast."],"lemma":"smear","lemmaPos":"verb","synonyms":["daubed","sullied","spread"],"number":"singular","pastTenses":"smeared","tense":"past","isIrregular":false,"source":"smeared"}