{"transcript":"dɪˈdʒɛnəˌreɪtɪd","exists":true,"definitions":["Declined in quality or character.","Worsened or deteriorated.","Underwent degeneration."],"examples":["The debate degenerated into a shouting match.","His health degenerated rapidly.","The once-beautiful garden had degenerated into a wilderness."],"lemma":"degenerate","lemmaPos":"verb","synonyms":["deteriorated","worsened","declined","decayed"],"number":"singular","pastTenses":"degenerated","tense":"past","isIrregular":false,"source":"degenerated"}