{"transcript":"ˈlɛðər","exists":true,"definitions":["To beat or flog someone with a leather strap.","To cover something with leather.","To polish or clean with a piece of leather."],"examples":["The old man would leather his boots until they shone.","He threatened to leather the disobedient child.","They decided to leather the new sofa."],"lemma":"leather","lemmaPos":"verb","synonyms":["flog","strap","beat","cover","polish"],"number":"singular","pastTenses":"leathered","tense":"present","isIrregular":false,"source":"leather"}