{"transcript":"liːd ʌp tuː","exists":true,"definitions":["To serve as a prelude or introduction to something.","To gradually approach or prepare for something."],"examples":["The events of the day led up to the big announcement.","His early research led up to his groundbreaking discovery.","The small talk led up to the main topic of discussion."],"lemma":"lead up to","lemmaPos":"verb","synonyms":["precede","foreshadow","prepare for","introduce"],"number":"singular","pastTenses":"led up to, led up to","tense":"present","isIrregular":true,"source":"lead up to"}